snake_mip_solver/__init__.py
snake_mip_solver/generator.py
snake_mip_solver/puzzle.py
snake_mip_solver/solver.py
snake_mip_solver-0.3.0.dist-info/licenses/LICENSE
snake_mip_solver-0.3.0.dist-info/METADATA
snake_mip_solver-0.3.0.dist-info/WHEEL
snake_mip_solver-0.3.0.dist-info/top_level.txt
snake_mip_solver-0.3.0.dist-info/RECORD
