Metadata-Version: 2.4
Name: snake-mip-solver
Version: 0.3.0
Summary: A Snake puzzle solver using Mixed Integer Programming (MIP)
Author: Rasmus Ørnstrup Mikkelsen
License-Expression: MIT
Project-URL: Documentation, https://github.com/DenHvideDvaerg/snake-mip-solver/blob/main/model.md
Project-URL: Homepage, https://github.com/DenHvideDvaerg/snake-mip-solver
Project-URL: Bug Reports, https://github.com/DenHvideDvaerg/snake-mip-solver/issues
Project-URL: Source, https://github.com/DenHvideDvaerg/snake-mip-solver
Keywords: puzzle,solver,mixed-integer-programming,optimization,snake
Classifier: Programming Language :: Python :: 3
Classifier: Programming Language :: Python :: 3.9
Classifier: Programming Language :: Python :: 3.10
Classifier: Programming Language :: Python :: 3.11
Classifier: Programming Language :: Python :: 3.12
Classifier: Programming Language :: Python :: 3.13
Classifier: Topic :: Games/Entertainment :: Puzzle Games
Classifier: Topic :: Scientific/Engineering :: Mathematics
Classifier: Operating System :: OS Independent
Requires-Python: >=3.9
License-File: LICENSE
Requires-Dist: ortools
Dynamic: license-file
